Workbook

Sheet How to Use
B1: Mobile Auto Detailer Business Tracker
B2: One workbook for a mobile detailing business. Enter each job, expense, supply purchase and trip once; the Dashboard, Summary and Customers tabs fill in from those entries.
B4: How to Use
A5: 1 | B5: Dashboard: type the tax year and your tax set-aside % in the yellow cells (and your odometer readings on January 1 and December 31 if you want your business-use %). Charts and key figures update as you add entries.
A6: 2 | B6: Jobs: add one row per job with the date, customer, vehicle, service, payment method, amount and any tip, and mark Paid? Yes or No. This one row counts as income and updates that customer's history.
A7: 3 | B7: Customers: add each customer once, before their first job, so their name appears in the Jobs dropdown. Jobs, Total Spent, Unpaid Balance and Last Visit fill in automatically.
A8: 4 | B8: Expenses: add business bills and purchases other than detailing supplies, with a category.
A9: 5 | B9: Supplies: add chemicals, towels, pads and equipment here (not on Expenses). They count as costs automatically, and Cost per Job shows what each supply costs you per job.
A10: 6 | B10: Mileage Log: add one row per business trip. IRS Rate and Deduction fill in from the IRS Rates tab.
A11: 7 | B11: Summary: month-by-month income, costs, profit and mileage for the chosen tax year.
A12: 8 | B12: Lists: edit the dropdown choices (services, payment methods, expense and supply categories).
B14: Good to know
B15: Each data tab has room for 500 entries and Customers for 200. Only entries dated in the Dashboard's tax year count toward the totals.
B16: Profit After Mileage subtracts the IRS standard mileage deduction from Net Profit. If you use the standard mileage rate, don't also enter fuel or vehicle repairs as expenses for that vehicle.
B17: The tax set-aside is a savings target, not a tax calculation. Many self-employed people put aside 25-30% of profit; ask a tax professional what fits you.
B18: IRS rates included: $0.70/mile from January 1, 2025; $0.725/mile from January 1, 2026; $0.76/mile from July 1, 2026. Check irs.gov for the current rate and add new ones on the IRS Rates tab.
B19: Customer details are personal information. Store this file securely and don't share it.
B20: This product is a record-keeping tool and is not tax advice. Tax rules change and depend on your situation; confirm deductions with a qualified tax professional or irs.gov.
B22: White table cells and yellow cells are for your entries. Grey cells calculate automatically; don't type over them.

Sheet Dashboard
A1: Detailing Business Dashboard
A2: Type in the yellow cells. Everything else updates from your entries.
A4: Settings
A5: Tax Year | B5: 2026
A6: Tax Set-Aside % | B6: 0.25
A7: Odometer on January 1
A8: Odometer on December 31
A10: Key Figures
A11: Total Income | B11: =Summary!$B$19
A12: Total Costs | B12: =Summary!$C$19+Summary!$D$19
A13: Net Profit | B13: =Summary!$E$19
A14: Profit Margin | B14: =IF(B11=0,0,B13/B11)
A15: Mileage Deduction | B15: =Summary!$F$19
A16: Profit After Mileage | B16: =Summary!$G$19
A17: Tax Set-Aside | B17: =ROUND(MAX(0,B16)*B6,2)
A18: Take-Home After Set-Aside | B18: =B16-B17
A19: Jobs Completed | B19: =COUNTIFS('Jobs'!$A$2:$A$501,">="&DATE(Dashboard!$B$5,1,1),'Jobs'!$A$2:$A$501,"<"&DATE(Dashboard!$B$5+1,1,1))
A20: Unpaid Balance | B20: =SUMIF('Jobs'!$I$2:$I$501,"No",'Jobs'!$H$2:$H$501)
A21: Business Miles | B21: =SUMIFS('Mileage Log'!$F$2:$F$501,'Mileage Log'!$A$2:$A$501,">="&DATE(Dashboard!$B$5,1,1),'Mileage Log'!$A$2:$A$501,"<"&DATE(Dashboard!$B$5+1,1,1))
A22: Total Miles Driven | B22: =IF(AND(ISNUMBER(B7),ISNUMBER(B8)),B8-B7,"")
A23: Business Use % | B23: =IF(ISNUMBER(B22),IF(B22>0,B21/B22,""),"")
A25: Unpaid Balance counts every unpaid job, whatever the year. The tax set-aside is a savings target, not a tax calculation. Many self-employed people put aside 25-30% of profit; ask a tax professional what fits you.

Sheet Jobs
A1: Date | B1: Customer Name | C1: Vehicle | D1: Service | E1: Payment Method | F1: Service Amount | G1: Tip | H1: Total | I1: Paid? | J1: Notes
H2: =IF(COUNT(F2:G2)=0,"",SUM(F2:G2))
H3: =IF(COUNT(F3:G3)=0,"",SUM(F3:G3))
H4: =IF(COUNT(F4:G4)=0,"",SUM(F4:G4))
H5: =IF(COUNT(F5:G5)=0,"",SUM(F5:G5))
H6: =IF(COUNT(F6:G6)=0,"",SUM(F6:G6))
H7: =IF(COUNT(F7:G7)=0,"",SUM(F7:G7))
H8: =IF(COUNT(F8:G8)=0,"",SUM(F8:G8))
H9: =IF(COUNT(F9:G9)=0,"",SUM(F9:G9))
H10: =IF(COUNT(F10:G10)=0,"",SUM(F10:G10))
H11: =IF(COUNT(F11:G11)=0,"",SUM(F11:G11))
H12: =IF(COUNT(F12:G12)=0,"",SUM(F12:G12))
H13: =IF(COUNT(F13:G13)=0,"",SUM(F13:G13))
... H501: =IF(COUNT(F501:G501)=0,"",SUM(F501:G501))

Sheet Expenses
A1: Date | B1: Vendor | C1: Category | D1: Description | E1: Payment Method | F1: Amount | G1: Notes

Sheet Supplies
A1: Date | B1: Supplier | C1: Product | D1: Category | E1: Quantity | F1: Unit | G1: Cost per Unit | H1: Total Cost | I1: Jobs per Unit | J1: Cost per Job | K1: Notes
H2: =IF(COUNT(E2,G2)<2,"",ROUND(E2*G2,2)) | J2: =IF(AND(ISNUMBER(G2),ISNUMBER(I2)),IF(I2>0,ROUND(G2/I2,2),""),"")
H3: =IF(COUNT(E3,G3)<2,"",ROUND(E3*G3,2)) | J3: =IF(AND(ISNUMBER(G3),ISNUMBER(I3)),IF(I3>0,ROUND(G3/I3,2),""),"")
H4: =IF(COUNT(E4,G4)<2,"",ROUND(E4*G4,2)) | J4: =IF(AND(ISNUMBER(G4),ISNUMBER(I4)),IF(I4>0,ROUND(G4/I4,2),""),"")
H5: =IF(COUNT(E5,G5)<2,"",ROUND(E5*G5,2)) | J5: =IF(AND(ISNUMBER(G5),ISNUMBER(I5)),IF(I5>0,ROUND(G5/I5,2),""),"")
H6: =IF(COUNT(E6,G6)<2,"",ROUND(E6*G6,2)) | J6: =IF(AND(ISNUMBER(G6),ISNUMBER(I6)),IF(I6>0,ROUND(G6/I6,2),""),"")
H7: =IF(COUNT(E7,G7)<2,"",ROUND(E7*G7,2)) | J7: =IF(AND(ISNUMBER(G7),ISNUMBER(I7)),IF(I7>0,ROUND(G7/I7,2),""),"")
H8: =IF(COUNT(E8,G8)<2,"",ROUND(E8*G8,2)) | J8: =IF(AND(ISNUMBER(G8),ISNUMBER(I8)),IF(I8>0,ROUND(G8/I8,2),""),"")
H9: =IF(COUNT(E9,G9)<2,"",ROUND(E9*G9,2)) | J9: =IF(AND(ISNUMBER(G9),ISNUMBER(I9)),IF(I9>0,ROUND(G9/I9,2),""),"")
H10: =IF(COUNT(E10,G10)<2,"",ROUND(E10*G10,2)) | J10: =IF(AND(ISNUMBER(G10),ISNUMBER(I10)),IF(I10>0,ROUND(G10/I10,2),""),"")
H11: =IF(COUNT(E11,G11)<2,"",ROUND(E11*G11,2)) | J11: =IF(AND(ISNUMBER(G11),ISNUMBER(I11)),IF(I11>0,ROUND(G11/I11,2),""),"")
H12: =IF(COUNT(E12,G12)<2,"",ROUND(E12*G12,2)) | J12: =IF(AND(ISNUMBER(G12),ISNUMBER(I12)),IF(I12>0,ROUND(G12/I12,2),""),"")
H13: =IF(COUNT(E13,G13)<2,"",ROUND(E13*G13,2)) | J13: =IF(AND(ISNUMBER(G13),ISNUMBER(I13)),IF(I13>0,ROUND(G13/I13,2),""),"")
... H501: =IF(COUNT(E501,G501)<2,"",ROUND(E501*G501,2)) | J501: =IF(AND(ISNUMBER(G501),ISNUMBER(I501)),IF(I501>0,ROUND(G501/I501,2),""),"")

Sheet Mileage Log
A1: Date | B1: Business Purpose | C1: Customer / Job | D1: From | E1: To | F1: Business Miles | G1: IRS Rate | H1: Deduction | I1: Notes
G2: =IF(ISNUMBER(A2),IF(A2<MIN('IRS Rates'!$A$2:$A$21),"No rate",VLOOKUP(A2,'IRS Rates'!$A$2:$B$21,2,TRUE)),"") | H2: =IF(AND(ISNUMBER(F2),ISNUMBER(G2)),ROUND(F2*G2,2),"")
G3: =IF(ISNUMBER(A3),IF(A3<MIN('IRS Rates'!$A$2:$A$21),"No rate",VLOOKUP(A3,'IRS Rates'!$A$2:$B$21,2,TRUE)),"") | H3: =IF(AND(ISNUMBER(F3),ISNUMBER(G3)),ROUND(F3*G3,2),"")
G4: =IF(ISNUMBER(A4),IF(A4<MIN('IRS Rates'!$A$2:$A$21),"No rate",VLOOKUP(A4,'IRS Rates'!$A$2:$B$21,2,TRUE)),"") | H4: =IF(AND(ISNUMBER(F4),ISNUMBER(G4)),ROUND(F4*G4,2),"")
G5: =IF(ISNUMBER(A5),IF(A5<MIN('IRS Rates'!$A$2:$A$21),"No rate",VLOOKUP(A5,'IRS Rates'!$A$2:$B$21,2,TRUE)),"") | H5: =IF(AND(ISNUMBER(F5),ISNUMBER(G5)),ROUND(F5*G5,2),"")
G6: =IF(ISNUMBER(A6),IF(A6<MIN('IRS Rates'!$A$2:$A$21),"No rate",VLOOKUP(A6,'IRS Rates'!$A$2:$B$21,2,TRUE)),"") | H6: =IF(AND(ISNUMBER(F6),ISNUMBER(G6)),ROUND(F6*G6,2),"")
G7: =IF(ISNUMBER(A7),IF(A7<MIN('IRS Rates'!$A$2:$A$21),"No rate",VLOOKUP(A7,'IRS Rates'!$A$2:$B$21,2,TRUE)),"") | H7: =IF(AND(ISNUMBER(F7),ISNUMBER(G7)),ROUND(F7*G7,2),"")
G8: =IF(ISNUMBER(A8),IF(A8<MIN('IRS Rates'!$A$2:$A$21),"No rate",VLOOKUP(A8,'IRS Rates'!$A$2:$B$21,2,TRUE)),"") | H8: =IF(AND(ISNUMBER(F8),ISNUMBER(G8)),ROUND(F8*G8,2),"")
G9: =IF(ISNUMBER(A9),IF(A9<MIN('IRS Rates'!$A$2:$A$21),"No rate",VLOOKUP(A9,'IRS Rates'!$A$2:$B$21,2,TRUE)),"") | H9: =IF(AND(ISNUMBER(F9),ISNUMBER(G9)),ROUND(F9*G9,2),"")
G10: =IF(ISNUMBER(A10),IF(A10<MIN('IRS Rates'!$A$2:$A$21),"No rate",VLOOKUP(A10,'IRS Rates'!$A$2:$B$21,2,TRUE)),"") | H10: =IF(AND(ISNUMBER(F10),ISNUMBER(G10)),ROUND(F10*G10,2),"")
G11: =IF(ISNUMBER(A11),IF(A11<MIN('IRS Rates'!$A$2:$A$21),"No rate",VLOOKUP(A11,'IRS Rates'!$A$2:$B$21,2,TRUE)),"") | H11: =IF(AND(ISNUMBER(F11),ISNUMBER(G11)),ROUND(F11*G11,2),"")
G12: =IF(ISNUMBER(A12),IF(A12<MIN('IRS Rates'!$A$2:$A$21),"No rate",VLOOKUP(A12,'IRS Rates'!$A$2:$B$21,2,TRUE)),"") | H12: =IF(AND(ISNUMBER(F12),ISNUMBER(G12)),ROUND(F12*G12,2),"")
G13: =IF(ISNUMBER(A13),IF(A13<MIN('IRS Rates'!$A$2:$A$21),"No rate",VLOOKUP(A13,'IRS Rates'!$A$2:$B$21,2,TRUE)),"") | H13: =IF(AND(ISNUMBER(F13),ISNUMBER(G13)),ROUND(F13*G13,2),"")
... G501: =IF(ISNUMBER(A501),IF(A501<MIN('IRS Rates'!$A$2:$A$21),"No rate",VLOOKUP(A501,'IRS Rates'!$A$2:$B$21,2,TRUE)),"") | H501: =IF(AND(ISNUMBER(F501),ISNUMBER(G501)),ROUND(F501*G501,2),"")

Sheet Customers
A1: Customer Name | B1: Phone | C1: Email | D1: Service Address | E1: Vehicle(s) | F1: Preferred Service | G1: Jobs | H1: Total Spent | I1: Unpaid Balance | J1: Last Visit | K1: Notes
G2: =IF(A2="","",COUNTIF('Jobs'!$B$2:$B$501,A2)) | H2: =IF(A2="","",SUMIF('Jobs'!$B$2:$B$501,A2,'Jobs'!$H$2:$H$501)) | I2: =IF(A2="","",SUMIFS('Jobs'!$H$2:$H$501,'Jobs'!$B$2:$B$501,A2,'Jobs'!$I$2:$I$501,"No")) | J2: =IF(A2="","",IF(COUNTIF('Jobs'!$B$2:$B$501,A2)=0,"",SUMPRODUCT(MAX(('Jobs'!$B$2:$B$501=A2)*'Jobs'!$A$2:$A$501))))
G3: =IF(A3="","",COUNTIF('Jobs'!$B$2:$B$501,A3)) | H3: =IF(A3="","",SUMIF('Jobs'!$B$2:$B$501,A3,'Jobs'!$H$2:$H$501)) | I3: =IF(A3="","",SUMIFS('Jobs'!$H$2:$H$501,'Jobs'!$B$2:$B$501,A3,'Jobs'!$I$2:$I$501,"No")) | J3: =IF(A3="","",IF(COUNTIF('Jobs'!$B$2:$B$501,A3)=0,"",SUMPRODUCT(MAX(('Jobs'!$B$2:$B$501=A3)*'Jobs'!$A$2:$A$501))))
G4: =IF(A4="","",COUNTIF('Jobs'!$B$2:$B$501,A4)) | H4: =IF(A4="","",SUMIF('Jobs'!$B$2:$B$501,A4,'Jobs'!$H$2:$H$501)) | I4: =IF(A4="","",SUMIFS('Jobs'!$H$2:$H$501,'Jobs'!$B$2:$B$501,A4,'Jobs'!$I$2:$I$501,"No")) | J4: =IF(A4="","",IF(COUNTIF('Jobs'!$B$2:$B$501,A4)=0,"",SUMPRODUCT(MAX(('Jobs'!$B$2:$B$501=A4)*'Jobs'!$A$2:$A$501))))
G5: =IF(A5="","",COUNTIF('Jobs'!$B$2:$B$501,A5)) | H5: =IF(A5="","",SUMIF('Jobs'!$B$2:$B$501,A5,'Jobs'!$H$2:$H$501)) | I5: =IF(A5="","",SUMIFS('Jobs'!$H$2:$H$501,'Jobs'!$B$2:$B$501,A5,'Jobs'!$I$2:$I$501,"No")) | J5: =IF(A5="","",IF(COUNTIF('Jobs'!$B$2:$B$501,A5)=0,"",SUMPRODUCT(MAX(('Jobs'!$B$2:$B$501=A5)*'Jobs'!$A$2:$A$501))))
G6: =IF(A6="","",COUNTIF('Jobs'!$B$2:$B$501,A6)) | H6: =IF(A6="","",SUMIF('Jobs'!$B$2:$B$501,A6,'Jobs'!$H$2:$H$501)) | I6: =IF(A6="","",SUMIFS('Jobs'!$H$2:$H$501,'Jobs'!$B$2:$B$501,A6,'Jobs'!$I$2:$I$501,"No")) | J6: =IF(A6="","",IF(COUNTIF('Jobs'!$B$2:$B$501,A6)=0,"",SUMPRODUCT(MAX(('Jobs'!$B$2:$B$501=A6)*'Jobs'!$A$2:$A$501))))
G7: =IF(A7="","",COUNTIF('Jobs'!$B$2:$B$501,A7)) | H7: =IF(A7="","",SUMIF('Jobs'!$B$2:$B$501,A7,'Jobs'!$H$2:$H$501)) | I7: =IF(A7="","",SUMIFS('Jobs'!$H$2:$H$501,'Jobs'!$B$2:$B$501,A7,'Jobs'!$I$2:$I$501,"No")) | J7: =IF(A7="","",IF(COUNTIF('Jobs'!$B$2:$B$501,A7)=0,"",SUMPRODUCT(MAX(('Jobs'!$B$2:$B$501=A7)*'Jobs'!$A$2:$A$501))))
G8: =IF(A8="","",COUNTIF('Jobs'!$B$2:$B$501,A8)) | H8: =IF(A8="","",SUMIF('Jobs'!$B$2:$B$501,A8,'Jobs'!$H$2:$H$501)) | I8: =IF(A8="","",SUMIFS('Jobs'!$H$2:$H$501,'Jobs'!$B$2:$B$501,A8,'Jobs'!$I$2:$I$501,"No")) | J8: =IF(A8="","",IF(COUNTIF('Jobs'!$B$2:$B$501,A8)=0,"",SUMPRODUCT(MAX(('Jobs'!$B$2:$B$501=A8)*'Jobs'!$A$2:$A$501))))
G9: =IF(A9="","",COUNTIF('Jobs'!$B$2:$B$501,A9)) | H9: =IF(A9="","",SUMIF('Jobs'!$B$2:$B$501,A9,'Jobs'!$H$2:$H$501)) | I9: =IF(A9="","",SUMIFS('Jobs'!$H$2:$H$501,'Jobs'!$B$2:$B$501,A9,'Jobs'!$I$2:$I$501,"No")) | J9: =IF(A9="","",IF(COUNTIF('Jobs'!$B$2:$B$501,A9)=0,"",SUMPRODUCT(MAX(('Jobs'!$B$2:$B$501=A9)*'Jobs'!$A$2:$A$501))))
G10: =IF(A10="","",COUNTIF('Jobs'!$B$2:$B$501,A10)) | H10: =IF(A10="","",SUMIF('Jobs'!$B$2:$B$501,A10,'Jobs'!$H$2:$H$501)) | I10: =IF(A10="","",SUMIFS('Jobs'!$H$2:$H$501,'Jobs'!$B$2:$B$501,A10,'Jobs'!$I$2:$I$501,"No")) | J10: =IF(A10="","",IF(COUNTIF('Jobs'!$B$2:$B$501,A10)=0,"",SUMPRODUCT(MAX(('Jobs'!$B$2:$B$501=A10)*'Jobs'!$A$2:$A$501))))
G11: =IF(A11="","",COUNTIF('Jobs'!$B$2:$B$501,A11)) | H11: =IF(A11="","",SUMIF('Jobs'!$B$2:$B$501,A11,'Jobs'!$H$2:$H$501)) | I11: =IF(A11="","",SUMIFS('Jobs'!$H$2:$H$501,'Jobs'!$B$2:$B$501,A11,'Jobs'!$I$2:$I$501,"No")) | J11: =IF(A11="","",IF(COUNTIF('Jobs'!$B$2:$B$501,A11)=0,"",SUMPRODUCT(MAX(('Jobs'!$B$2:$B$501=A11)*'Jobs'!$A$2:$A$501))))
G12: =IF(A12="","",COUNTIF('Jobs'!$B$2:$B$501,A12)) | H12: =IF(A12="","",SUMIF('Jobs'!$B$2:$B$501,A12,'Jobs'!$H$2:$H$501)) | I12: =IF(A12="","",SUMIFS('Jobs'!$H$2:$H$501,'Jobs'!$B$2:$B$501,A12,'Jobs'!$I$2:$I$501,"No")) | J12: =IF(A12="","",IF(COUNTIF('Jobs'!$B$2:$B$501,A12)=0,"",SUMPRODUCT(MAX(('Jobs'!$B$2:$B$501=A12)*'Jobs'!$A$2:$A$501))))
G13: =IF(A13="","",COUNTIF('Jobs'!$B$2:$B$501,A13)) | H13: =IF(A13="","",SUMIF('Jobs'!$B$2:$B$501,A13,'Jobs'!$H$2:$H$501)) | I13: =IF(A13="","",SUMIFS('Jobs'!$H$2:$H$501,'Jobs'!$B$2:$B$501,A13,'Jobs'!$I$2:$I$501,"No")) | J13: =IF(A13="","",IF(COUNTIF('Jobs'!$B$2:$B$501,A13)=0,"",SUMPRODUCT(MAX(('Jobs'!$B$2:$B$501=A13)*'Jobs'!$A$2:$A$501))))
... G201: =IF(A201="","",COUNTIF('Jobs'!$B$2:$B$501,A201)) | H201: =IF(A201="","",SUMIF('Jobs'!$B$2:$B$501,A201,'Jobs'!$H$2:$H$501)) | I201: =IF(A201="","",SUMIFS('Jobs'!$H$2:$H$501,'Jobs'!$B$2:$B$501,A201,'Jobs'!$I$2:$I$501,"No")) | J201: =IF(A201="","",IF(COUNTIF('Jobs'!$B$2:$B$501,A201)=0,"",SUMPRODUCT(MAX(('Jobs'!$B$2:$B$501=A201)*'Jobs'!$A$2:$A$501))))

Sheet Summary
A1: Monthly Summary
A2: Totals for the tax year set on the Dashboard. Supplies count as costs.
A4: Tax Year | B4: =Dashboard!$B$5
A6: Month | B6: Income | C6: Expenses | D6: Supplies | E6: Net Profit | F6: Mileage Deduction | G6: Profit After Mileage | I6: Costs by Category | J6: Amount | L6: Supplies by Category | M6: Amount
A7: January | B7: =SUMIFS('Jobs'!$H$2:$H$501,'Jobs'!$A$2:$A$501,">="&DATE(Dashboard!$B$5,1,1),'Jobs'!$A$2:$A$501,"<"&DATE(Dashboard!$B$5,2,1)) | C7: =SUMIFS('Expenses'!$F$2:$F$501,'Expenses'!$A$2:$A$501,">="&DATE(Dashboard!$B$5,1,1),'Expenses'!$A$2:$A$501,"<"&DATE(Dashboard!$B$5,2,1)) | D7: =SUMIFS('Supplies'!$H$2:$H$501,'Supplies'!$A$2:$A$501,">="&DATE(Dashboard!$B$5,1,1),'Supplies'!$A$2:$A$501,"<"&DATE(Dashboard!$B$5,2,1)) | E7: =B7-C7-D7 | F7: =SUMIFS('Mileage Log'!$H$2:$H$501,'Mileage Log'!$A$2:$A$501,">="&DATE(Dashboard!$B$5,1,1),'Mileage Log'!$A$2:$A$501,"<"&DATE(Dashboard!$B$5,2,1)) | G7: =E7-F7 | I7: Supplies | J7: =D19 | L7: =IF(Lists!$D2="","",Lists!$D2) | M7: =IF(L7="","",SUMIFS('Supplies'!$H$2:$H$501,'Supplies'!$D$2:$D$501,L7,'Supplies'!$A$2:$A$501,">="&DATE(Dashboard!$B$5,1,1),'Supplies'!$A$2:$A$501,"<"&DATE(Dashboard!$B$5+1,1,1)))
A8: February | B8: =SUMIFS('Jobs'!$H$2:$H$501,'Jobs'!$A$2:$A$501,">="&DATE(Dashboard!$B$5,2,1),'Jobs'!$A$2:$A$501,"<"&DATE(Dashboard!$B$5,3,1)) | C8: =SUMIFS('Expenses'!$F$2:$F$501,'Expenses'!$A$2:$A$501,">="&DATE(Dashboard!$B$5,2,1),'Expenses'!$A$2:$A$501,"<"&DATE(Dashboard!$B$5,3,1)) | D8: =SUMIFS('Supplies'!$H$2:$H$501,'Supplies'!$A$2:$A$501,">="&DATE(Dashboard!$B$5,2,1),'Supplies'!$A$2:$A$501,"<"&DATE(Dashboard!$B$5,3,1)) | E8: =B8-C8-D8 | F8: =SUMIFS('Mileage Log'!$H$2:$H$501,'Mileage Log'!$A$2:$A$501,">="&DATE(Dashboard!$B$5,2,1),'Mileage Log'!$A$2:$A$501,"<"&DATE(Dashboard!$B$5,3,1)) | G8: =E8-F8 | I8: =IF(Lists!$C2="","",Lists!$C2) | J8: =IF(I8="","",SUMIFS('Expenses'!$F$2:$F$501,'Expenses'!$C$2:$C$501,I8,'Expenses'!$A$2:$A$501,">="&DATE(Dashboard!$B$5,1,1),'Expenses'!$A$2:$A$501,"<"&DATE(Dashboard!$B$5+1,1,1))) | L8: =IF(Lists!$D3="","",Lists!$D3) | M8: =IF(L8="","",SUMIFS('Supplies'!$H$2:$H$501,'Supplies'!$D$2:$D$501,L8,'Supplies'!$A$2:$A$501,">="&DATE(Dashboard!$B$5,1,1),'Supplies'!$A$2:$A$501,"<"&DATE(Dashboard!$B$5+1,1,1)))
A9: March | B9: =SUMIFS('Jobs'!$H$2:$H$501,'Jobs'!$A$2:$A$501,">="&DATE(Dashboard!$B$5,3,1),'Jobs'!$A$2:$A$501,"<"&DATE(Dashboard!$B$5,4,1)) | C9: =SUMIFS('Expenses'!$F$2:$F$501,'Expenses'!$A$2:$A$501,">="&DATE(Dashboard!$B$5,3,1),'Expenses'!$A$2:$A$501,"<"&DATE(Dashboard!$B$5,4,1)) | D9: =SUMIFS('Supplies'!$H$2:$H$501,'Supplies'!$A$2:$A$501,">="&DATE(Dashboard!$B$5,3,1),'Supplies'!$A$2:$A$501,"<"&DATE(Dashboard!$B$5,4,1)) | E9: =B9-C9-D9 | F9: =SUMIFS('Mileage Log'!$H$2:$H$501,'Mileage Log'!$A$2:$A$501,">="&DATE(Dashboard!$B$5,3,1),'Mileage Log'!$A$2:$A$501,"<"&DATE(Dashboard!$B$5,4,1)) | G9: =E9-F9 | I9: =IF(Lists!$C3="","",Lists!$C3) | J9: =IF(I9="","",SUMIFS('Expenses'!$F$2:$F$501,'Expenses'!$C$2:$C$501,I9,'Expenses'!$A$2:$A$501,">="&DATE(Dashboard!$B$5,1,1),'Expenses'!$A$2:$A$501,"<"&DATE(Dashboard!$B$5+1,1,1))) | L9: =IF(Lists!$D4="","",Lists!$D4) | M9: =IF(L9="","",SUMIFS('Supplies'!$H$2:$H$501,'Supplies'!$D$2:$D$501,L9,'Supplies'!$A$2:$A$501,">="&DATE(Dashboard!$B$5,1,1),'Supplies'!$A$2:$A$501,"<"&DATE(Dashboard!$B$5+1,1,1)))
A10: April | B10: =SUMIFS('Jobs'!$H$2:$H$501,'Jobs'!$A$2:$A$501,">="&DATE(Dashboard!$B$5,4,1),'Jobs'!$A$2:$A$501,"<"&DATE(Dashboard!$B$5,5,1)) | C10: =SUMIFS('Expenses'!$F$2:$F$501,'Expenses'!$A$2:$A$501,">="&DATE(Dashboard!$B$5,4,1),'Expenses'!$A$2:$A$501,"<"&DATE(Dashboard!$B$5,5,1)) | D10: =SUMIFS('Supplies'!$H$2:$H$501,'Supplies'!$A$2:$A$501,">="&DATE(Dashboard!$B$5,4,1),'Supplies'!$A$2:$A$501,"<"&DATE(Dashboard!$B$5,5,1)) | E10: =B10-C10-D10 | F10: =SUMIFS('Mileage Log'!$H$2:$H$501,'Mileage Log'!$A$2:$A$501,">="&DATE(Dashboard!$B$5,4,1),'Mileage Log'!$A$2:$A$501,"<"&DATE(Dashboard!$B$5,5,1)) | G10: =E10-F10 | I10: =IF(Lists!$C4="","",Lists!$C4) | J10: =IF(I10="","",SUMIFS('Expenses'!$F$2:$F$501,'Expenses'!$C$2:$C$501,I10,'Expenses'!$A$2:$A$501,">="&DATE(Dashboard!$B$5,1,1),'Expenses'!$A$2:$A$501,"<"&DATE(Dashboard!$B$5+1,1,1))) | L10: =IF(Lists!$D5="","",Lists!$D5) | M10: =IF(L10="","",SUMIFS('Supplies'!$H$2:$H$501,'Supplies'!$D$2:$D$501,L10,'Supplies'!$A$2:$A$501,">="&DATE(Dashboard!$B$5,1,1),'Supplies'!$A$2:$A$501,"<"&DATE(Dashboard!$B$5+1,1,1)))
A11: May | B11: =SUMIFS('Jobs'!$H$2:$H$501,'Jobs'!$A$2:$A$501,">="&DATE(Dashboard!$B$5,5,1),'Jobs'!$A$2:$A$501,"<"&DATE(Dashboard!$B$5,6,1)) | C11: =SUMIFS('Expenses'!$F$2:$F$501,'Expenses'!$A$2:$A$501,">="&DATE(Dashboard!$B$5,5,1),'Expenses'!$A$2:$A$501,"<"&DATE(Dashboard!$B$5,6,1)) | D11: =SUMIFS('Supplies'!$H$2:$H$501,'Supplies'!$A$2:$A$501,">="&DATE(Dashboard!$B$5,5,1),'Supplies'!$A$2:$A$501,"<"&DATE(Dashboard!$B$5,6,1)) | E11: =B11-C11-D11 | F11: =SUMIFS('Mileage Log'!$H$2:$H$501,'Mileage Log'!$A$2:$A$501,">="&DATE(Dashboard!$B$5,5,1),'Mileage Log'!$A$2:$A$501,"<"&DATE(Dashboard!$B$5,6,1)) | G11: =E11-F11 | I11: =IF(Lists!$C5="","",Lists!$C5) | J11: =IF(I11="","",SUMIFS('Expenses'!$F$2:$F$501,'Expenses'!$C$2:$C$501,I11,'Expenses'!$A$2:$A$501,">="&DATE(Dashboard!$B$5,1,1),'Expenses'!$A$2:$A$501,"<"&DATE(Dashboard!$B$5+1,1,1))) | L11: =IF(Lists!$D6="","",Lists!$D6) | M11: =IF(L11="","",SUMIFS('Supplies'!$H$2:$H$501,'Supplies'!$D$2:$D$501,L11,'Supplies'!$A$2:$A$501,">="&DATE(Dashboard!$B$5,1,1),'Supplies'!$A$2:$A$501,"<"&DATE(Dashboard!$B$5+1,1,1)))
A12: June | B12: =SUMIFS('Jobs'!$H$2:$H$501,'Jobs'!$A$2:$A$501,">="&DATE(Dashboard!$B$5,6,1),'Jobs'!$A$2:$A$501,"<"&DATE(Dashboard!$B$5,7,1)) | C12: =SUMIFS('Expenses'!$F$2:$F$501,'Expenses'!$A$2:$A$501,">="&DATE(Dashboard!$B$5,6,1),'Expenses'!$A$2:$A$501,"<"&DATE(Dashboard!$B$5,7,1)) | D12: =SUMIFS('Supplies'!$H$2:$H$501,'Supplies'!$A$2:$A$501,">="&DATE(Dashboard!$B$5,6,1),'Supplies'!$A$2:$A$501,"<"&DATE(Dashboard!$B$5,7,1)) | E12: =B12-C12-D12 | F12: =SUMIFS('Mileage Log'!$H$2:$H$501,'Mileage Log'!$A$2:$A$501,">="&DATE(Dashboard!$B$5,6,1),'Mileage Log'!$A$2:$A$501,"<"&DATE(Dashboard!$B$5,7,1)) | G12: =E12-F12 | I12: =IF(Lists!$C6="","",Lists!$C6) | J12: =IF(I12="","",SUMIFS('Expenses'!$F$2:$F$501,'Expenses'!$C$2:$C$501,I12,'Expenses'!$A$2:$A$501,">="&DATE(Dashboard!$B$5,1,1),'Expenses'!$A$2:$A$501,"<"&DATE(Dashboard!$B$5+1,1,1))) | L12: =IF(Lists!$D7="","",Lists!$D7) | M12: =IF(L12="","",SUMIFS('Supplies'!$H$2:$H$501,'Supplies'!$D$2:$D$501,L12,'Supplies'!$A$2:$A$501,">="&DATE(Dashboard!$B$5,1,1),'Supplies'!$A$2:$A$501,"<"&DATE(Dashboard!$B$5+1,1,1)))
A13: July | B13: =SUMIFS('Jobs'!$H$2:$H$501,'Jobs'!$A$2:$A$501,">="&DATE(Dashboard!$B$5,7,1),'Jobs'!$A$2:$A$501,"<"&DATE(Dashboard!$B$5,8,1)) | C13: =SUMIFS('Expenses'!$F$2:$F$501,'Expenses'!$A$2:$A$501,">="&DATE(Dashboard!$B$5,7,1),'Expenses'!$A$2:$A$501,"<"&DATE(Dashboard!$B$5,8,1)) | D13: =SUMIFS('Supplies'!$H$2:$H$501,'Supplies'!$A$2:$A$501,">="&DATE(Dashboard!$B$5,7,1),'Supplies'!$A$2:$A$501,"<"&DATE(Dashboard!$B$5,8,1)) | E13: =B13-C13-D13 | F13: =SUMIFS('Mileage Log'!$H$2:$H$501,'Mileage Log'!$A$2:$A$501,">="&DATE(Dashboard!$B$5,7,1),'Mileage Log'!$A$2:$A$501,"<"&DATE(Dashboard!$B$5,8,1)) | G13: =E13-F13 | I13: =IF(Lists!$C7="","",Lists!$C7) | J13: =IF(I13="","",SUMIFS('Expenses'!$F$2:$F$501,'Expenses'!$C$2:$C$501,I13,'Expenses'!$A$2:$A$501,">="&DATE(Dashboard!$B$5,1,1),'Expenses'!$A$2:$A$501,"<"&DATE(Dashboard!$B$5+1,1,1))) | L13: =IF(Lists!$D8="","",Lists!$D8) | M13: =IF(L13="","",SUMIFS('Supplies'!$H$2:$H$501,'Supplies'!$D$2:$D$501,L13,'Supplies'!$A$2:$A$501,">="&DATE(Dashboard!$B$5,1,1),'Supplies'!$A$2:$A$501,"<"&DATE(Dashboard!$B$5+1,1,1)))
A14: August | B14: =SUMIFS('Jobs'!$H$2:$H$501,'Jobs'!$A$2:$A$501,">="&DATE(Dashboard!$B$5,8,1),'Jobs'!$A$2:$A$501,"<"&DATE(Dashboard!$B$5,9,1)) | C14: =SUMIFS('Expenses'!$F$2:$F$501,'Expenses'!$A$2:$A$501,">="&DATE(Dashboard!$B$5,8,1),'Expenses'!$A$2:$A$501,"<"&DATE(Dashboard!$B$5,9,1)) | D14: =SUMIFS('Supplies'!$H$2:$H$501,'Supplies'!$A$2:$A$501,">="&DATE(Dashboard!$B$5,8,1),'Supplies'!$A$2:$A$501,"<"&DATE(Dashboard!$B$5,9,1)) | E14: =B14-C14-D14 | F14: =SUMIFS('Mileage Log'!$H$2:$H$501,'Mileage Log'!$A$2:$A$501,">="&DATE(Dashboard!$B$5,8,1),'Mileage Log'!$A$2:$A$501,"<"&DATE(Dashboard!$B$5,9,1)) | G14: =E14-F14 | I14: =IF(Lists!$C8="","",Lists!$C8) | J14: =IF(I14="","",SUMIFS('Expenses'!$F$2:$F$501,'Expenses'!$C$2:$C$501,I14,'Expenses'!$A$2:$A$501,">="&DATE(Dashboard!$B$5,1,1),'Expenses'!$A$2:$A$501,"<"&DATE(Dashboard!$B$5+1,1,1))) | L14: =IF(Lists!$D9="","",Lists!$D9) | M14: =IF(L14="","",SUMIFS('Supplies'!$H$2:$H$501,'Supplies'!$D$2:$D$501,L14,'Supplies'!$A$2:$A$501,">="&DATE(Dashboard!$B$5,1,1),'Supplies'!$A$2:$A$501,"<"&DATE(Dashboard!$B$5+1,1,1)))
A15: September | B15: =SUMIFS('Jobs'!$H$2:$H$501,'Jobs'!$A$2:$A$501,">="&DATE(Dashboard!$B$5,9,1),'Jobs'!$A$2:$A$501,"<"&DATE(Dashboard!$B$5,10,1)) | C15: =SUMIFS('Expenses'!$F$2:$F$501,'Expenses'!$A$2:$A$501,">="&DATE(Dashboard!$B$5,9,1),'Expenses'!$A$2:$A$501,"<"&DATE(Dashboard!$B$5,10,1)) | D15: =SUMIFS('Supplies'!$H$2:$H$501,'Supplies'!$A$2:$A$501,">="&DATE(Dashboard!$B$5,9,1),'Supplies'!$A$2:$A$501,"<"&DATE(Dashboard!$B$5,10,1)) | E15: =B15-C15-D15 | F15: =SUMIFS('Mileage Log'!$H$2:$H$501,'Mileage Log'!$A$2:$A$501,">="&DATE(Dashboard!$B$5,9,1),'Mileage Log'!$A$2:$A$501,"<"&DATE(Dashboard!$B$5,10,1)) | G15: =E15-F15 | I15: =IF(Lists!$C9="","",Lists!$C9) | J15: =IF(I15="","",SUMIFS('Expenses'!$F$2:$F$501,'Expenses'!$C$2:$C$501,I15,'Expenses'!$A$2:$A$501,">="&DATE(Dashboard!$B$5,1,1),'Expenses'!$A$2:$A$501,"<"&DATE(Dashboard!$B$5+1,1,1))) | L15: =IF(Lists!$D10="","",Lists!$D10) | M15: =IF(L15="","",SUMIFS('Supplies'!$H$2:$H$501,'Supplies'!$D$2:$D$501,L15,'Supplies'!$A$2:$A$501,">="&DATE(Dashboard!$B$5,1,1),'Supplies'!$A$2:$A$501,"<"&DATE(Dashboard!$B$5+1,1,1)))
A16: October | B16: =SUMIFS('Jobs'!$H$2:$H$501,'Jobs'!$A$2:$A$501,">="&DATE(Dashboard!$B$5,10,1),'Jobs'!$A$2:$A$501,"<"&DATE(Dashboard!$B$5,11,1)) | C16: =SUMIFS('Expenses'!$F$2:$F$501,'Expenses'!$A$2:$A$501,">="&DATE(Dashboard!$B$5,10,1),'Expenses'!$A$2:$A$501,"<"&DATE(Dashboard!$B$5,11,1)) | D16: =SUMIFS('Supplies'!$H$2:$H$501,'Supplies'!$A$2:$A$501,">="&DATE(Dashboard!$B$5,10,1),'Supplies'!$A$2:$A$501,"<"&DATE(Dashboard!$B$5,11,1)) | E16: =B16-C16-D16 | F16: =SUMIFS('Mileage Log'!$H$2:$H$501,'Mileage Log'!$A$2:$A$501,">="&DATE(Dashboard!$B$5,10,1),'Mileage Log'!$A$2:$A$501,"<"&DATE(Dashboard!$B$5,11,1)) | G16: =E16-F16 | I16: =IF(Lists!$C10="","",Lists!$C10) | J16: =IF(I16="","",SUMIFS('Expenses'!$F$2:$F$501,'Expenses'!$C$2:$C$501,I16,'Expenses'!$A$2:$A$501,">="&DATE(Dashboard!$B$5,1,1),'Expenses'!$A$2:$A$501,"<"&DATE(Dashboard!$B$5+1,1,1))) | L16: =IF(Lists!$D11="","",Lists!$D11) | M16: =IF(L16="","",SUMIFS('Supplies'!$H$2:$H$501,'Supplies'!$D$2:$D$501,L16,'Supplies'!$A$2:$A$501,">="&DATE(Dashboard!$B$5,1,1),'Supplies'!$A$2:$A$501,"<"&DATE(Dashboard!$B$5+1,1,1)))
A17: November | B17: =SUMIFS('Jobs'!$H$2:$H$501,'Jobs'!$A$2:$A$501,">="&DATE(Dashboard!$B$5,11,1),'Jobs'!$A$2:$A$501,"<"&DATE(Dashboard!$B$5,12,1)) | C17: =SUMIFS('Expenses'!$F$2:$F$501,'Expenses'!$A$2:$A$501,">="&DATE(Dashboard!$B$5,11,1),'Expenses'!$A$2:$A$501,"<"&DATE(Dashboard!$B$5,12,1)) | D17: =SUMIFS('Supplies'!$H$2:$H$501,'Supplies'!$A$2:$A$501,">="&DATE(Dashboard!$B$5,11,1),'Supplies'!$A$2:$A$501,"<"&DATE(Dashboard!$B$5,12,1)) | E17: =B17-C17-D17 | F17: =SUMIFS('Mileage Log'!$H$2:$H$501,'Mileage Log'!$A$2:$A$501,">="&DATE(Dashboard!$B$5,11,1),'Mileage Log'!$A$2:$A$501,"<"&DATE(Dashboard!$B$5,12,1)) | G17: =E17-F17 | I17: =IF(Lists!$C11="","",Lists!$C11) | J17: =IF(I17="","",SUMIFS('Expenses'!$F$2:$F$501,'Expenses'!$C$2:$C$501,I17,'Expenses'!$A$2:$A$501,">="&DATE(Dashboard!$B$5,1,1),'Expenses'!$A$2:$A$501,"<"&DATE(Dashboard!$B$5+1,1,1))) | L17: =IF(Lists!$D12="","",Lists!$D12) | M17: =IF(L17="","",SUMIFS('Supplies'!$H$2:$H$501,'Supplies'!$D$2:$D$501,L17,'Supplies'!$A$2:$A$501,">="&DATE(Dashboard!$B$5,1,1),'Supplies'!$A$2:$A$501,"<"&DATE(Dashboard!$B$5+1,1,1)))
A18: December | B18: =SUMIFS('Jobs'!$H$2:$H$501,'Jobs'!$A$2:$A$501,">="&DATE(Dashboard!$B$5,12,1),'Jobs'!$A$2:$A$501,"<"&DATE(Dashboard!$B$5,13,1)) | C18: =SUMIFS('Expenses'!$F$2:$F$501,'Expenses'!$A$2:$A$501,">="&DATE(Dashboard!$B$5,12,1),'Expenses'!$A$2:$A$501,"<"&DATE(Dashboard!$B$5,13,1)) | D18: =SUMIFS('Supplies'!$H$2:$H$501,'Supplies'!$A$2:$A$501,">="&DATE(Dashboard!$B$5,12,1),'Supplies'!$A$2:$A$501,"<"&DATE(Dashboard!$B$5,13,1)) | E18: =B18-C18-D18 | F18: =SUMIFS('Mileage Log'!$H$2:$H$501,'Mileage Log'!$A$2:$A$501,">="&DATE(Dashboard!$B$5,12,1),'Mileage Log'!$A$2:$A$501,"<"&DATE(Dashboard!$B$5,13,1)) | G18: =E18-F18 | I18: =IF(Lists!$C12="","",Lists!$C12) | J18: =IF(I18="","",SUMIFS('Expenses'!$F$2:$F$501,'Expenses'!$C$2:$C$501,I18,'Expenses'!$A$2:$A$501,">="&DATE(Dashboard!$B$5,1,1),'Expenses'!$A$2:$A$501,"<"&DATE(Dashboard!$B$5+1,1,1))) | L18: =IF(Lists!$D13="","",Lists!$D13) | M18: =IF(L18="","",SUMIFS('Supplies'!$H$2:$H$501,'Supplies'!$D$2:$D$501,L18,'Supplies'!$A$2:$A$501,">="&DATE(Dashboard!$B$5,1,1),'Supplies'!$A$2:$A$501,"<"&DATE(Dashboard!$B$5+1,1,1)))
A19: Total | B19: =SUM(B7:B18) | C19: =SUM(C7:C18) | D19: =SUM(D7:D18) | E19: =SUM(E7:E18) | F19: =SUM(F7:F18) | G19: =SUM(G7:G18) | I19: =IF(Lists!$C13="","",Lists!$C13) | J19: =IF(I19="","",SUMIFS('Expenses'!$F$2:$F$501,'Expenses'!$C$2:$C$501,I19,'Expenses'!$A$2:$A$501,">="&DATE(Dashboard!$B$5,1,1),'Expenses'!$A$2:$A$501,"<"&DATE(Dashboard!$B$5+1,1,1))) | L19: =IF(Lists!$D14="","",Lists!$D14) | M19: =IF(L19="","",SUMIFS('Supplies'!$H$2:$H$501,'Supplies'!$D$2:$D$501,L19,'Supplies'!$A$2:$A$501,">="&DATE(Dashboard!$B$5,1,1),'Supplies'!$A$2:$A$501,"<"&DATE(Dashboard!$B$5+1,1,1)))
I20: =IF(Lists!$C14="","",Lists!$C14) | J20: =IF(I20="","",SUMIFS('Expenses'!$F$2:$F$501,'Expenses'!$C$2:$C$501,I20,'Expenses'!$A$2:$A$501,">="&DATE(Dashboard!$B$5,1,1),'Expenses'!$A$2:$A$501,"<"&DATE(Dashboard!$B$5+1,1,1))) | L20: =IF(Lists!$D15="","",Lists!$D15) | M20: =IF(L20="","",SUMIFS('Supplies'!$H$2:$H$501,'Supplies'!$D$2:$D$501,L20,'Supplies'!$A$2:$A$501,">="&DATE(Dashboard!$B$5,1,1),'Supplies'!$A$2:$A$501,"<"&DATE(Dashboard!$B$5+1,1,1)))
I21: =IF(Lists!$C15="","",Lists!$C15) | J21: =IF(I21="","",SUMIFS('Expenses'!$F$2:$F$501,'Expenses'!$C$2:$C$501,I21,'Expenses'!$A$2:$A$501,">="&DATE(Dashboard!$B$5,1,1),'Expenses'!$A$2:$A$501,"<"&DATE(Dashboard!$B$5+1,1,1))) | L21: =IF(Lists!$D16="","",Lists!$D16) | M21: =IF(L21="","",SUMIFS('Supplies'!$H$2:$H$501,'Supplies'!$D$2:$D$501,L21,'Supplies'!$A$2:$A$501,">="&DATE(Dashboard!$B$5,1,1),'Supplies'!$A$2:$A$501,"<"&DATE(Dashboard!$B$5+1,1,1)))
I22: =IF(Lists!$C16="","",Lists!$C16) | J22: =IF(I22="","",SUMIFS('Expenses'!$F$2:$F$501,'Expenses'!$C$2:$C$501,I22,'Expenses'!$A$2:$A$501,">="&DATE(Dashboard!$B$5,1,1),'Expenses'!$A$2:$A$501,"<"&DATE(Dashboard!$B$5+1,1,1))) | L22: =IF(Lists!$D17="","",Lists!$D17) | M22: =IF(L22="","",SUMIFS('Supplies'!$H$2:$H$501,'Supplies'!$D$2:$D$501,L22,'Supplies'!$A$2:$A$501,">="&DATE(Dashboard!$B$5,1,1),'Supplies'!$A$2:$A$501,"<"&DATE(Dashboard!$B$5+1,1,1)))
I23: =IF(Lists!$C17="","",Lists!$C17) | J23: =IF(I23="","",SUMIFS('Expenses'!$F$2:$F$501,'Expenses'!$C$2:$C$501,I23,'Expenses'!$A$2:$A$501,">="&DATE(Dashboard!$B$5,1,1),'Expenses'!$A$2:$A$501,"<"&DATE(Dashboard!$B$5+1,1,1))) | L23: =IF(Lists!$D18="","",Lists!$D18) | M23: =IF(L23="","",SUMIFS('Supplies'!$H$2:$H$501,'Supplies'!$D$2:$D$501,L23,'Supplies'!$A$2:$A$501,">="&DATE(Dashboard!$B$5,1,1),'Supplies'!$A$2:$A$501,"<"&DATE(Dashboard!$B$5+1,1,1)))
I24: =IF(Lists!$C18="","",Lists!$C18) | J24: =IF(I24="","",SUMIFS('Expenses'!$F$2:$F$501,'Expenses'!$C$2:$C$501,I24,'Expenses'!$A$2:$A$501,">="&DATE(Dashboard!$B$5,1,1),'Expenses'!$A$2:$A$501,"<"&DATE(Dashboard!$B$5+1,1,1))) | L24: =IF(Lists!$D19="","",Lists!$D19) | M24: =IF(L24="","",SUMIFS('Supplies'!$H$2:$H$501,'Supplies'!$D$2:$D$501,L24,'Supplies'!$A$2:$A$501,">="&DATE(Dashboard!$B$5,1,1),'Supplies'!$A$2:$A$501,"<"&DATE(Dashboard!$B$5+1,1,1)))
I25: =IF(Lists!$C19="","",Lists!$C19) | J25: =IF(I25="","",SUMIFS('Expenses'!$F$2:$F$501,'Expenses'!$C$2:$C$501,I25,'Expenses'!$A$2:$A$501,">="&DATE(Dashboard!$B$5,1,1),'Expenses'!$A$2:$A$501,"<"&DATE(Dashboard!$B$5+1,1,1))) | L25: =IF(Lists!$D20="","",Lists!$D20) | M25: =IF(L25="","",SUMIFS('Supplies'!$H$2:$H$501,'Supplies'!$D$2:$D$501,L25,'Supplies'!$A$2:$A$501,">="&DATE(Dashboard!$B$5,1,1),'Supplies'!$A$2:$A$501,"<"&DATE(Dashboard!$B$5+1,1,1)))
I26: =IF(Lists!$C20="","",Lists!$C20) | J26: =IF(I26="","",SUMIFS('Expenses'!$F$2:$F$501,'Expenses'!$C$2:$C$501,I26,'Expenses'!$A$2:$A$501,">="&DATE(Dashboard!$B$5,1,1),'Expenses'!$A$2:$A$501,"<"&DATE(Dashboard!$B$5+1,1,1))) | L26: =IF(Lists!$D21="","",Lists!$D21) | M26: =IF(L26="","",SUMIFS('Supplies'!$H$2:$H$501,'Supplies'!$D$2:$D$501,L26,'Supplies'!$A$2:$A$501,">="&DATE(Dashboard!$B$5,1,1),'Supplies'!$A$2:$A$501,"<"&DATE(Dashboard!$B$5+1,1,1)))
I27: =IF(Lists!$C21="","",Lists!$C21) | J27: =IF(I27="","",SUMIFS('Expenses'!$F$2:$F$501,'Expenses'!$C$2:$C$501,I27,'Expenses'!$A$2:$A$501,">="&DATE(Dashboard!$B$5,1,1),'Expenses'!$A$2:$A$501,"<"&DATE(Dashboard!$B$5+1,1,1))) | L27: =IF(Lists!$D22="","",Lists!$D22) | M27: =IF(L27="","",SUMIFS('Supplies'!$H$2:$H$501,'Supplies'!$D$2:$D$501,L27,'Supplies'!$A$2:$A$501,">="&DATE(Dashboard!$B$5,1,1),'Supplies'!$A$2:$A$501,"<"&DATE(Dashboard!$B$5+1,1,1)))
I28: =IF(Lists!$C22="","",Lists!$C22) | J28: =IF(I28="","",SUMIFS('Expenses'!$F$2:$F$501,'Expenses'!$C$2:$C$501,I28,'Expenses'!$A$2:$A$501,">="&DATE(Dashboard!$B$5,1,1),'Expenses'!$A$2:$A$501,"<"&DATE(Dashboard!$B$5+1,1,1))) | L28: =IF(Lists!$D23="","",Lists!$D23) | M28: =IF(L28="","",SUMIFS('Supplies'!$H$2:$H$501,'Supplies'!$D$2:$D$501,L28,'Supplies'!$A$2:$A$501,">="&DATE(Dashboard!$B$5,1,1),'Supplies'!$A$2:$A$501,"<"&DATE(Dashboard!$B$5+1,1,1)))
I29: =IF(Lists!$C23="","",Lists!$C23) | J29: =IF(I29="","",SUMIFS('Expenses'!$F$2:$F$501,'Expenses'!$C$2:$C$501,I29,'Expenses'!$A$2:$A$501,">="&DATE(Dashboard!$B$5,1,1),'Expenses'!$A$2:$A$501,"<"&DATE(Dashboard!$B$5+1,1,1))) | L29: =IF(Lists!$D24="","",Lists!$D24) | M29: =IF(L29="","",SUMIFS('Supplies'!$H$2:$H$501,'Supplies'!$D$2:$D$501,L29,'Supplies'!$A$2:$A$501,">="&DATE(Dashboard!$B$5,1,1),'Supplies'!$A$2:$A$501,"<"&DATE(Dashboard!$B$5+1,1,1)))
I30: =IF(Lists!$C24="","",Lists!$C24) | J30: =IF(I30="","",SUMIFS('Expenses'!$F$2:$F$501,'Expenses'!$C$2:$C$501,I30,'Expenses'!$A$2:$A$501,">="&DATE(Dashboard!$B$5,1,1),'Expenses'!$A$2:$A$501,"<"&DATE(Dashboard!$B$5+1,1,1))) | L30: =IF(Lists!$D25="","",Lists!$D25) | M30: =IF(L30="","",SUMIFS('Supplies'!$H$2:$H$501,'Supplies'!$D$2:$D$501,L30,'Supplies'!$A$2:$A$501,">="&DATE(Dashboard!$B$5,1,1),'Supplies'!$A$2:$A$501,"<"&DATE(Dashboard!$B$5+1,1,1)))
I31: =IF(Lists!$C25="","",Lists!$C25) | J31: =IF(I31="","",SUMIFS('Expenses'!$F$2:$F$501,'Expenses'!$C$2:$C$501,I31,'Expenses'!$A$2:$A$501,">="&DATE(Dashboard!$B$5,1,1),'Expenses'!$A$2:$A$501,"<"&DATE(Dashboard!$B$5+1,1,1))) | L31: =IF(Lists!$D26="","",Lists!$D26) | M31: =IF(L31="","",SUMIFS('Supplies'!$H$2:$H$501,'Supplies'!$D$2:$D$501,L31,'Supplies'!$A$2:$A$501,">="&DATE(Dashboard!$B$5,1,1),'Supplies'!$A$2:$A$501,"<"&DATE(Dashboard!$B$5+1,1,1)))
... I36: =IF(Lists!$C30="","",Lists!$C30) | J36: =IF(I36="","",SUMIFS('Expenses'!$F$2:$F$501,'Expenses'!$C$2:$C$501,I36,'Expenses'!$A$2:$A$501,">="&DATE(Dashboard!$B$5,1,1),'Expenses'!$A$2:$A$501,"<"&DATE(Dashboard!$B$5+1,1,1))) | L36: =IF(Lists!$D31="","",Lists!$D31) | M36: =IF(L36="","",SUMIFS('Supplies'!$H$2:$H$501,'Supplies'!$D$2:$D$501,L36,'Supplies'!$A$2:$A$501,">="&DATE(Dashboard!$B$5,1,1),'Supplies'!$A$2:$A$501,"<"&DATE(Dashboard!$B$5+1,1,1)))
I37: =IF(Lists!$C31="","",Lists!$C31) | J37: =IF(I37="","",SUMIFS('Expenses'!$F$2:$F$501,'Expenses'!$C$2:$C$501,I37,'Expenses'!$A$2:$A$501,">="&DATE(Dashboard!$B$5,1,1),'Expenses'!$A$2:$A$501,"<"&DATE(Dashboard!$B$5+1,1,1)))

Sheet IRS Rates
A1: Effective From | B1: Rate per Mile | C1: Source
A2: 45658 | B2: 0.7 | C2: IRS Notice 2025-5
A3: 46023 | B3: 0.725 | C3: IRS Notice 2026-10
A4: 46204 | B4: 0.76 | C4: IRS Announcement 2026-11

Sheet Lists
A1: Services | B1: Payment Methods | C1: Expense Categories | D1: Supply Categories
A2: Exterior Wash | B2: Cash | C2: Equipment & Tools | D2: Chemicals
A3: Interior Detail | B3: Card | C3: Fuel | D3: Towels & Microfiber
A4: Full Detail | B4: Venmo | C4: Vehicle Repairs & Maintenance | D4: Pads & Brushes
A5: Wax & Sealant | B5: Zelle | C5: Insurance | D5: Equipment
A6: Paint Correction | B6: Cash App | C6: Marketing & Advertising | D6: Water & Power
A7: Ceramic Coating | B7: PayPal | C7: Phone & Software | D7: Safety & PPE
A8: Headlight Restoration | B8: Check | C8: Water & Utilities | D8: Other
A9: Engine Bay | B9: Other | C9: Licenses & Fees
A10: Odor Removal | C10: Training
A11: Fleet Wash | C11: Other
A12: Other
